bombsquad/__init__.py
bombsquad/bombsquad.py
bombsquad-0.1.2.dist-info/METADATA
bombsquad-0.1.2.dist-info/WHEEL
bombsquad-0.1.2.dist-info/licenses/LICENSE
bombsquad-0.1.2.dist-info/RECORD
