Metadata-Version: 2.4
Name: bombsquad
Version: 0.1.2
Summary: Isolate OOM-prone functions in a separate process, raise exceptions on SIGKILL or segfault
License: MIT
License-File: LICENSE
Author: Ben Skubi
Author-email: skubi@ohsu.edu
Requires-Python: >=3.10
Classifier: License :: OSI Approved :: MIT License
Classifier: Programming Language :: Python :: 3
Classifier: Programming Language :: Python :: 3.10
Classifier: Programming Language :: Python :: 3.11
Classifier: Programming Language :: Python :: 3.12
Classifier: Programming Language :: Python :: 3.13
Classifier: Programming Language :: Python :: 3.14
Requires-Dist: dill
